wetest/scrcpy/__init__.py
wetest/scrcpy/api.py
wetest/scrcpy/const.py
wetest/scrcpy/core/__init__.py
wetest/scrcpy/core/_audio.py
wetest/scrcpy/core/_const.py
wetest/scrcpy/core/_control.py
wetest/scrcpy/core/_deprecated.py
wetest/scrcpy/core/_device.py
wetest/scrcpy/core/_exceptions.py
wetest/scrcpy/core/_log.py
wetest/scrcpy/core/_recorder.py
wetest/scrcpy/core/_socket.py
wetest/scrcpy/core/_video.py
wetest/scrcpy/launcher.py
wetest/scrcpy/output_server.log
wetest/scrcpy/resource/android/libjpeg-turbo/arm64/libjpeg-turbo.so
wetest/scrcpy/resource/android/scrcpy-server
wetest/scrcpy/wdblogs/wdb.20251127.log
wetest_scrcpy-0.3.3.dist-info/METADATA
wetest_scrcpy-0.3.3.dist-info/WHEEL
wetest_scrcpy-0.3.3.dist-info/RECORD
