Metadata-Version: 2.4
Name: wetest-scrcpy
Version: 0.3.3
Summary: Wetest Scrcpy is a lightweight Python framework based on the scrcpy protocol, supporting screenshot and screen recording for both Android and iOS devices.
Author: WeTest
Author-email: wetest@tencent.com
Requires-Python: >=3.8
Classifier: Programming Language :: Python :: 3
Classifier: Programming Language :: Python :: 3.8
Classifier: Programming Language :: Python :: 3.9
Classifier: Programming Language :: Python :: 3.10
Classifier: Programming Language :: Python :: 3.11
Classifier: Programming Language :: Python :: 3.12
Classifier: Programming Language :: Python :: 3.13
Classifier: Programming Language :: Python :: 3.14
Requires-Dist: adbutils (>=2.9.3,<3.0.0)
Requires-Dist: av (<=12.3.0)
Requires-Dist: construct (>=2.10.70,<3.0.0)
Requires-Dist: numpy (>=1.21.0,<2.0.0) ; python_version < "3.12"
Requires-Dist: numpy (>=1.26.0,<2.0.0) ; python_version >= "3.12"
Requires-Dist: opencv-python (>=4.8.0,<4.10.0)
Requires-Dist: pydantic (<=2.10.6)
Requires-Dist: wetest-osplatform (>=0.0.2,<0.0.3)
Requires-Dist: wetest-pyidb (>=0.0.2,<0.0.3)
